xfetus/__init__.py
xfetus/xfetus.py
xfetus-0.0.7.dist-info/METADATA
xfetus-0.0.7.dist-info/WHEEL
xfetus-0.0.7.dist-info/top_level.txt
xfetus-0.0.7.dist-info/RECORD
