Metadata-Version: 2.1
Name: xfetus
Version: 0.0.7
Summary: Python-based library for Synthesis of Ultrasound Fetal Imaging
Author: Miguel Xochicale
License: MIT
Project-URL: Source, https://github.com/budai4medtech/xfetus
Project-URL: Tracker, https://github.com/budai4medtech/xfetus/issues
Keywords: artificial intelligence,diffusion models
Classifier: Development Status :: 2 - Pre-Alpha
Classifier: Intended Audience :: Developers
Classifier: Topic :: Scientific/Engineering :: Artificial Intelligence
Classifier: License :: OSI Approved :: MIT License
Classifier: Programming Language :: Python :: 3
Requires-Python: >=3.8
Requires-Dist: torch
Requires-Dist: notebook
Requires-Dist: pandas
Requires-Dist: scikit-image
